[{"amenagement_id":"pvo_patrimoine_voirie.pvoamenagementcyclable.3222","score":0.083991},
{"amenagement_id":"pvo_patrimoine_voirie.pvoamenagementcyclable.2833","score":0.092444},
{"amenagement_id":"pvo_patrimoine_voirie.pvoamenagementcyclable.4742","score":0.227797},
{"amenagement_id":"pvo_patrimoine_voirie.pvoamenagementcyclable.3960","score":0.227797},
{"amenagement_id":"pvo_patrimoine_voirie.pvoamenagementcyclable.3270","score":0.223528},
{"amenagement_id":"pvo_patrimoine_voirie.pvoamenagementcyclable.1966","score":0.183511},
{"amenagement_id":"pvo_patrimoine_voirie.pvoamenagementcyclable.208","score":0.183511},
{"amenagement_id":"pvo_patrimoine_voirie.pvoamenagementcyclable.2019","score":0.257582},
{"amenagement_id":"pvo_patrimoine_voirie.pvoamenagementcyclable.2189","score":0.257582},
{"amenagement_id":"pvo_patrimoine_voirie.pvoamenagementcyclable.3781","score":0.269581},
{"amenagement_id":"pvo_patrimoine_voirie.pvoamenagementcyclable.6052","score":0.269581},
{"amenagement_id":"pvo_patrimoine_voirie.pvoamenagementcyclable.204","score":0.238395},
{"amenagement_id":"pvo_patrimoine_voirie.pvoamenagementcyclable.2521","score":0.254519},
{"amenagement_id":"pvo_patrimoine_voirie.pvoamenagementcyclable.6983","score":0.254519},
{"amenagement_id":"pvo_patrimoine_voirie.pvoamenagementcyclable.2191"},
{"amenagement_id":"pvo_patrimoine_voirie.pvoamenagementcyclable.2018","score":0.209001},
{"amenagement_id":"pvo_patrimoine_voirie.pvoamenagementcyclable.1599","score":0.311525},
{"amenagement_id":"pvo_patrimoine_voirie.pvoamenagementcyclable.2171"},
{"amenagement_id":"pvo_patrimoine_voirie.pvoamenagementcyclable.6006"},
{"amenagement_id":"pvo_patrimoine_voirie.pvoamenagementcyclable.840","score":0.237638},
{"amenagement_id":"pvo_patrimoine_voirie.pvoamenagementcyclable.6533","score":0.332246},
{"amenagement_id":"pvo_patrimoine_voirie.pvoamenagementcyclable.716","score":0.332246},
{"amenagement_id":"pvo_patrimoine_voirie.pvoamenagementcyclable.6182","score":0.363905},
{"amenagement_id":"pvo_patrimoine_voirie.pvoamenagementcyclable.2887","score":0.378686},
{"amenagement_id":"pvo_patrimoine_voirie.pvoamenagementcyclable.2820","score":0.364949},
{"amenagement_id":"pvo_patrimoine_voirie.pvoamenagementcyclable.785","score":0.364949},
{"amenagement_id":"pvo_patrimoine_voirie.pvoamenagementcyclable.2628","score":0.331921},
{"amenagement_id":"pvo_patrimoine_voirie.pvoamenagementcyclable.2568","score":0.221117},
{"amenagement_id":"pvo_patrimoine_voirie.pvoamenagementcyclable.5993","score":0.221117},
{"amenagement_id":"pvo_patrimoine_voirie.pvoamenagementcyclable.382","score":0.30561},
{"amenagement_id":"pvo_patrimoine_voirie.pvoamenagementcyclable.2451","score":0.394056},
{"amenagement_id":"pvo_patrimoine_voirie.pvoamenagementcyclable.129","score":0.394056},
{"amenagement_id":"pvo_patrimoine_voirie.pvoamenagementcyclable.3406","score":0.317514},
{"amenagement_id":"pvo_patrimoine_voirie.pvoamenagementcyclable.1980","score":0.317514},
{"amenagement_id":"pvo_patrimoine_voirie.pvoamenagementcyclable.2665","score":0.438913},
{"amenagement_id":"pvo_patrimoine_voirie.pvoamenagementcyclable.2662","score":0.438913},
{"amenagement_id":"pvo_patrimoine_voirie.pvoamenagementcyclable.4091","score":0.412969},
{"amenagement_id":"pvo_patrimoine_voirie.pvoamenagementcyclable.784","score":0.412969},
{"amenagement_id":"pvo_patrimoine_voirie.pvoamenagementcyclable.474","score":0.435884},
{"amenagement_id":"pvo_patrimoine_voirie.pvoamenagementcyclable.2086","score":0.488914},
{"amenagement_id":"pvo_patrimoine_voirie.pvoamenagementcyclable.1919","score":0.488914},
{"amenagement_id":"pvo_patrimoine_voirie.pvoamenagementcyclable.1964","score":0.442655},
{"amenagement_id":"pvo_patrimoine_voirie.pvoamenagementcyclable.2060","score":0.50669},
{"amenagement_id":"pvo_patrimoine_voirie.pvoamenagementcyclable.795","score":0.50669},
{"amenagement_id":"pvo_patrimoine_voirie.pvoamenagementcyclable.337","score":0.377317},
{"amenagement_id":"pvo_patrimoine_voirie.pvoamenagementcyclable.4038","score":0.377317},
{"amenagement_id":"pvo_patrimoine_voirie.pvoamenagementcyclable.6700","score":0.502947},
{"amenagement_id":"pvo_patrimoine_voirie.pvoamenagementcyclable.6697","score":0.502947},
{"amenagement_id":"pvo_patrimoine_voirie.pvoamenagementcyclable.2363","score":0.489387},
{"amenagement_id":"pvo_patrimoine_voirie.pvoamenagementcyclable.3925","score":0.493414},
{"amenagement_id":"pvo_patrimoine_voirie.pvoamenagementcyclable.1588","score":0.493414},
{"amenagement_id":"pvo_patrimoine_voirie.pvoamenagementcyclable.5749","score":0.4932},
{"amenagement_id":"pvo_patrimoine_voirie.pvoamenagementcyclable.4582","score":0.519909},
{"amenagement_id":"pvo_patrimoine_voirie.pvoamenagementcyclable.1609","score":0.548595},
{"amenagement_id":"pvo_patrimoine_voirie.pvoamenagementcyclable.3985","score":0.534549},
{"amenagement_id":"pvo_patrimoine_voirie.pvoamenagementcyclable.1607","score":0.55886},
{"amenagement_id":"pvo_patrimoine_voirie.pvoamenagementcyclable.26","score":0.534704},
{"amenagement_id":"pvo_patrimoine_voirie.pvoamenagementcyclable.5865","score":0.534704},
{"amenagement_id":"pvo_patrimoine_voirie.pvoamenagementcyclable.2850","score":0.563586},
{"amenagement_id":"pvo_patrimoine_voirie.pvoamenagementcyclable.1718","score":0.561435},
{"amenagement_id":"pvo_patrimoine_voirie.pvoamenagementcyclable.7299","score":0.561435},
{"amenagement_id":"pvo_patrimoine_voirie.pvoamenagementcyclable.3159","score":0.602759},
{"amenagement_id":"pvo_patrimoine_voirie.pvoamenagementcyclable.3136","score":0.602759},
{"amenagement_id":"pvo_patrimoine_voirie.pvoamenagementcyclable.2358","score":0.621598},
{"amenagement_id":"pvo_patrimoine_voirie.pvoamenagementcyclable.6506","score":0.621598},
{"amenagement_id":"pvo_patrimoine_voirie.pvoamenagementcyclable.1676","score":0.621413},
{"amenagement_id":"pvo_patrimoine_voirie.pvoamenagementcyclable.7467","score":0.621413},
{"amenagement_id":"pvo_patrimoine_voirie.pvoamenagementcyclable.4895","score":0.607689},
{"amenagement_id":"pvo_patrimoine_voirie.pvoamenagementcyclable.5979","score":0.607689},
{"amenagement_id":"pvo_patrimoine_voirie.pvoamenagementcyclable.225","score":0.6495},
{"amenagement_id":"pvo_patrimoine_voirie.pvoamenagementcyclable.224","score":0.6495},
{"amenagement_id":"pvo_patrimoine_voirie.pvoamenagementcyclable.2940","score":0.637719},
{"amenagement_id":"pvo_patrimoine_voirie.pvoamenagementcyclable.4100","score":0.637719},
{"amenagement_id":"pvo_patrimoine_voirie.pvoamenagementcyclable.1936","score":0.64611},
{"amenagement_id":"pvo_patrimoine_voirie.pvoamenagementcyclable.2856"},
{"amenagement_id":"pvo_patrimoine_voirie.pvoamenagementcyclable.4090"},
{"amenagement_id":"pvo_patrimoine_voirie.pvoamenagementcyclable.2178","score":0.676444},
{"amenagement_id":"pvo_patrimoine_voirie.pvoamenagementcyclable.4195","score":0.679491},
{"amenagement_id":"pvo_patrimoine_voirie.pvoamenagementcyclable.2158","score":0.679491},
{"amenagement_id":"pvo_patrimoine_voirie.pvoamenagementcyclable.7103","score":0.67962},
{"amenagement_id":"pvo_patrimoine_voirie.pvoamenagementcyclable.4962","score":0.683602},
{"amenagement_id":"pvo_patrimoine_voirie.pvoamenagementcyclable.6266","score":0.683602},
{"amenagement_id":"pvo_patrimoine_voirie.pvoamenagementcyclable.2849","score":0.729506},
{"amenagement_id":"pvo_patrimoine_voirie.pvoamenagementcyclable.416","score":0.729506},
{"amenagement_id":"pvo_patrimoine_voirie.pvoamenagementcyclable.5982","score":0.728394},
{"amenagement_id":"pvo_patrimoine_voirie.pvoamenagementcyclable.303","score":0.746796},
{"amenagement_id":"pvo_patrimoine_voirie.pvoamenagementcyclable.3709","score":0.747226},
{"amenagement_id":"pvo_patrimoine_voirie.pvoamenagementcyclable.7163","score":0.747226},
{"amenagement_id":"pvo_patrimoine_voirie.pvoamenagementcyclable.6039","score":0.743657},
{"amenagement_id":"pvo_patrimoine_voirie.pvoamenagementcyclable.2487","score":0.749434},
{"amenagement_id":"pvo_patrimoine_voirie.pvoamenagementcyclable.2104","score":0.749434},
{"amenagement_id":"pvo_patrimoine_voirie.pvoamenagementcyclable.5774","score":0.759633},
{"amenagement_id":"pvo_patrimoine_voirie.pvoamenagementcyclable.6016","score":0.759633},
{"amenagement_id":"pvo_patrimoine_voirie.pvoamenagementcyclable.1509","score":0.768274},
{"amenagement_id":"pvo_patrimoine_voirie.pvoamenagementcyclable.4630","score":0.799258},
{"amenagement_id":"pvo_patrimoine_voirie.pvoamenagementcyclable.5864","score":0.799258},
{"amenagement_id":"pvo_patrimoine_voirie.pvoamenagementcyclable.718","score":0.81191},
{"amenagement_id":"pvo_patrimoine_voirie.pvoamenagementcyclable.3527"},
{"amenagement_id":"pvo_patrimoine_voirie.pvoamenagementcyclable.6503"},
{"amenagement_id":"pvo_patrimoine_voirie.pvoamenagementcyclable.5529","score":0.798988},
{"amenagement_id":"pvo_patrimoine_voirie.pvoamenagementcyclable.2033","score":0.798988},
{"amenagement_id":"pvo_patrimoine_voirie.pvoamenagementcyclable.2847","score":0.816693},
{"amenagement_id":"pvo_patrimoine_voirie.pvoamenagementcyclable.2697","score":0.829752},
{"amenagement_id":"pvo_patrimoine_voirie.pvoamenagementcyclable.2941","score":0.853189},
{"amenagement_id":"pvo_patrimoine_voirie.pvoamenagementcyclable.3539","score":0.862874},
{"amenagement_id":"pvo_patrimoine_voirie.pvoamenagementcyclable.4177","score":0.862874},
{"amenagement_id":"pvo_patrimoine_voirie.pvoamenagementcyclable.1909","score":0.867123},
{"amenagement_id":"pvo_patrimoine_voirie.pvoamenagementcyclable.4093","score":0.87685},
{"amenagement_id":"pvo_patrimoine_voirie.pvoamenagementcyclable.2845","score":0.87143},
{"amenagement_id":"pvo_patrimoine_voirie.pvoamenagementcyclable.4112","score":0.87143},
{"amenagement_id":"pvo_patrimoine_voirie.pvoamenagementcyclable.4265","score":0.87143}]
