[{"amenagement_id": "pvo_patrimoine_voirie.pvoamenagementcyclable.3337"},
{"amenagement_id": "pvo_patrimoine_voirie.pvoamenagementcyclable.3985","score":0.0},
{"amenagement_id": "pvo_patrimoine_voirie.pvoamenagementcyclable.6895","score":0.0},
{"amenagement_id": "pvo_patrimoine_voirie.pvoamenagementcyclable.6039","score":0.0},
{"amenagement_id": "pvo_patrimoine_voirie.pvoamenagementcyclable.6016","score":0.0},
{"amenagement_id": "pvo_patrimoine_voirie.pvoamenagementcyclable.3222","score":0.215232},
{"amenagement_id": "pvo_patrimoine_voirie.pvoamenagementcyclable.208"},
{"amenagement_id": "pvo_patrimoine_voirie.pvoamenagementcyclable.2833"},
{"amenagement_id": "pvo_patrimoine_voirie.pvoamenagementcyclable.752"},
{"amenagement_id": "pvo_patrimoine_voirie.pvoamenagementcyclable.3270","score":0.249765},
{"amenagement_id": "pvo_patrimoine_voirie.pvoamenagementcyclable.1675","score":0.210278},
{"amenagement_id": "pvo_patrimoine_voirie.pvoamenagementcyclable.6738","score":0.05458},
{"amenagement_id": "pvo_patrimoine_voirie.pvoamenagementcyclable.2019","score":0.294886},
{"amenagement_id": "pvo_patrimoine_voirie.pvoamenagementcyclable.2189","score":0.307285},
{"amenagement_id": "pvo_patrimoine_voirie.pvoamenagementcyclable.6894"},
{"amenagement_id": "pvo_patrimoine_voirie.pvoamenagementcyclable.3781","score":0.300273},
{"amenagement_id": "pvo_patrimoine_voirie.pvoamenagementcyclable.6052","score":0.308201},
{"amenagement_id": "pvo_patrimoine_voirie.pvoamenagementcyclable.3760","score":0.259424},
{"amenagement_id": "pvo_patrimoine_voirie.pvoamenagementcyclable.2191"},
{"amenagement_id": "pvo_patrimoine_voirie.pvoamenagementcyclable.3987"},
{"amenagement_id": "pvo_patrimoine_voirie.pvoamenagementcyclable.3960","score":0.319528},
{"amenagement_id": "pvo_patrimoine_voirie.pvoamenagementcyclable.1889","score":0.333934},
{"amenagement_id": "pvo_patrimoine_voirie.pvoamenagementcyclable.4742","score":0.331792},
{"amenagement_id": "pvo_patrimoine_voirie.pvoamenagementcyclable.2018","score":0.254584},
{"amenagement_id": "pvo_patrimoine_voirie.pvoamenagementcyclable.1722","score":0.340193},
{"amenagement_id": "pvo_patrimoine_voirie.pvoamenagementcyclable.840","score":0.296115},
{"amenagement_id": "pvo_patrimoine_voirie.pvoamenagementcyclable.2568","score":0.227499},
{"amenagement_id": "pvo_patrimoine_voirie.pvoamenagementcyclable.382","score":0.312303},
{"amenagement_id": "pvo_patrimoine_voirie.pvoamenagementcyclable.795","score":0.247063},
{"amenagement_id": "pvo_patrimoine_voirie.pvoamenagementcyclable.303","score":0.381117},
{"amenagement_id": "pvo_patrimoine_voirie.pvoamenagementcyclable.2060","score":0.291217},
{"amenagement_id": "pvo_patrimoine_voirie.pvoamenagementcyclable.2521","score":0.405192},
{"amenagement_id": "pvo_patrimoine_voirie.pvoamenagementcyclable.6983","score":0.408893},
{"amenagement_id": "pvo_patrimoine_voirie.pvoamenagementcyclable.2887","score":0.399605},
{"amenagement_id": "pvo_patrimoine_voirie.pvoamenagementcyclable.5993","score":0.299597},
{"amenagement_id": "pvo_patrimoine_voirie.pvoamenagementcyclable.785","score":0.412628},
{"amenagement_id": "pvo_patrimoine_voirie.pvoamenagementcyclable.3406","score":0.333408},
{"amenagement_id": "pvo_patrimoine_voirie.pvoamenagementcyclable.2820","score":0.42965},
{"amenagement_id": "pvo_patrimoine_voirie.pvoamenagementcyclable.1599","score":0.404142},
{"amenagement_id": "pvo_patrimoine_voirie.pvoamenagementcyclable.1980","score":0.359248},
{"amenagement_id": "pvo_patrimoine_voirie.pvoamenagementcyclable.1964"},
{"amenagement_id": "pvo_patrimoine_voirie.pvoamenagementcyclable.2858","score":0.411786},
{"amenagement_id": "pvo_patrimoine_voirie.pvoamenagementcyclable.6533","score":0.43774},
{"amenagement_id": "pvo_patrimoine_voirie.pvoamenagementcyclable.716","score":0.443201},
{"amenagement_id": "pvo_patrimoine_voirie.pvoamenagementcyclable.4090","score":0.389218},
{"amenagement_id": "pvo_patrimoine_voirie.pvoamenagementcyclable.2856","score":0.401702},
{"amenagement_id": "pvo_patrimoine_voirie.pvoamenagementcyclable.6006","score":0.434326},
{"amenagement_id": "pvo_patrimoine_voirie.pvoamenagementcyclable.2171","score":0.441463},
{"amenagement_id": "pvo_patrimoine_voirie.pvoamenagementcyclable.5353","score":0.471011},
{"amenagement_id": "pvo_patrimoine_voirie.pvoamenagementcyclable.5981","score":0.4879},
{"amenagement_id": "pvo_patrimoine_voirie.pvoamenagementcyclable.2628","score":0.479836},
{"amenagement_id": "pvo_patrimoine_voirie.pvoamenagementcyclable.4038","score":0.41872},
{"amenagement_id": "pvo_patrimoine_voirie.pvoamenagementcyclable.6352"},
{"amenagement_id": "pvo_patrimoine_voirie.pvoamenagementcyclable.3794","score":0.516705},
{"amenagement_id": "pvo_patrimoine_voirie.pvoamenagementcyclable.1919","score":0.517403},
{"amenagement_id": "pvo_patrimoine_voirie.pvoamenagementcyclable.7426","score":0.502911},
{"amenagement_id": "pvo_patrimoine_voirie.pvoamenagementcyclable.474","score":0.480009},
{"amenagement_id": "pvo_patrimoine_voirie.pvoamenagementcyclable.2086","score":0.537497},
{"amenagement_id": "pvo_patrimoine_voirie.pvoamenagementcyclable.2665","score":0.529873},
{"amenagement_id": "pvo_patrimoine_voirie.pvoamenagementcyclable.337","score":0.4769},
{"amenagement_id": "pvo_patrimoine_voirie.pvoamenagementcyclable.2662","score":0.543527},
{"amenagement_id": "pvo_patrimoine_voirie.pvoamenagementcyclable.4091","score":0.519042},
{"amenagement_id": "pvo_patrimoine_voirie.pvoamenagementcyclable.6697","score":0.537897},
{"amenagement_id": "pvo_patrimoine_voirie.pvoamenagementcyclable.784","score":0.533384},
{"amenagement_id": "pvo_patrimoine_voirie.pvoamenagementcyclable.6182","score":0.544725},
{"amenagement_id": "pvo_patrimoine_voirie.pvoamenagementcyclable.1721","score":0.50441},
{"amenagement_id": "pvo_patrimoine_voirie.pvoamenagementcyclable.2451","score":0.539327},
{"amenagement_id": "pvo_patrimoine_voirie.pvoamenagementcyclable.129","score":0.544186},
{"amenagement_id": "pvo_patrimoine_voirie.pvoamenagementcyclable.4582","score":0.543783},
{"amenagement_id": "pvo_patrimoine_voirie.pvoamenagementcyclable.2316","score":0.466005},
{"amenagement_id": "pvo_patrimoine_voirie.pvoamenagementcyclable.2849","score":0.591243},
{"amenagement_id": "pvo_patrimoine_voirie.pvoamenagementcyclable.1609","score":0.610916},
{"amenagement_id": "pvo_patrimoine_voirie.pvoamenagementcyclable.2737"},
{"amenagement_id": "pvo_patrimoine_voirie.pvoamenagementcyclable.4100","score":0.590504},
{"amenagement_id": "pvo_patrimoine_voirie.pvoamenagementcyclable.6700","score":0.605167},
{"amenagement_id": "pvo_patrimoine_voirie.pvoamenagementcyclable.1588","score":0.580962},
{"amenagement_id": "pvo_patrimoine_voirie.pvoamenagementcyclable.5865","score":0.608999},
{"amenagement_id": "pvo_patrimoine_voirie.pvoamenagementcyclable.2940","score":0.610223},
{"amenagement_id": "pvo_patrimoine_voirie.pvoamenagementcyclable.3925","score":0.597865},
{"amenagement_id": "pvo_patrimoine_voirie.pvoamenagementcyclable.2861","score":0.639324},
{"amenagement_id": "pvo_patrimoine_voirie.pvoamenagementcyclable.1936","score":0.610823},
{"amenagement_id": "pvo_patrimoine_voirie.pvoamenagementcyclable.1607","score":0.648529},
{"amenagement_id": "pvo_patrimoine_voirie.pvoamenagementcyclable.5749","score":0.56344},
{"amenagement_id": "pvo_patrimoine_voirie.pvoamenagementcyclable.224","score":0.653502},
{"amenagement_id": "pvo_patrimoine_voirie.pvoamenagementcyclable.2363","score":0.626069},
{"amenagement_id": "pvo_patrimoine_voirie.pvoamenagementcyclable.6506","score":0.660047},
{"amenagement_id": "pvo_patrimoine_voirie.pvoamenagementcyclable.6665","score":0.634747},
{"amenagement_id": "pvo_patrimoine_voirie.pvoamenagementcyclable.416","score":0.683208},
{"amenagement_id": "pvo_patrimoine_voirie.pvoamenagementcyclable.7103","score":0.66157},
{"amenagement_id": "pvo_patrimoine_voirie.pvoamenagementcyclable.225","score":0.680886},
{"amenagement_id": "pvo_patrimoine_voirie.pvoamenagementcyclable.3136","score":0.686137},
{"amenagement_id": "pvo_patrimoine_voirie.pvoamenagementcyclable.1676","score":0.564995},
{"amenagement_id": "pvo_patrimoine_voirie.pvoamenagementcyclable.2850","score":0.683053},
{"amenagement_id": "pvo_patrimoine_voirie.pvoamenagementcyclable.2358","score":0.69706},
{"amenagement_id": "pvo_patrimoine_voirie.pvoamenagementcyclable.26","score":0.707322},
{"amenagement_id": "pvo_patrimoine_voirie.pvoamenagementcyclable.7467","score":0.587151},
{"amenagement_id": "pvo_patrimoine_voirie.pvoamenagementcyclable.4895","score":0.682},
{"amenagement_id": "pvo_patrimoine_voirie.pvoamenagementcyclable.2178","score":0.651282},
{"amenagement_id": "pvo_patrimoine_voirie.pvoamenagementcyclable.5529","score":0.704487},
{"amenagement_id": "pvo_patrimoine_voirie.pvoamenagementcyclable.5979","score":0.724037},
{"amenagement_id": "pvo_patrimoine_voirie.pvoamenagementcyclable.6266","score":0.663144},
{"amenagement_id": "pvo_patrimoine_voirie.pvoamenagementcyclable.6038","score":0.678252},
{"amenagement_id": "pvo_patrimoine_voirie.pvoamenagementcyclable.5982","score":0.731155},
{"amenagement_id": "pvo_patrimoine_voirie.pvoamenagementcyclable.7299","score":0.733289},
{"amenagement_id": "pvo_patrimoine_voirie.pvoamenagementcyclable.1718","score":0.739386},
{"amenagement_id": "pvo_patrimoine_voirie.pvoamenagementcyclable.4630","score":0.683111},
{"amenagement_id": "pvo_patrimoine_voirie.pvoamenagementcyclable.2661","score":0.701135},
{"amenagement_id": "pvo_patrimoine_voirie.pvoamenagementcyclable.3159","score":0.782551},
{"amenagement_id": "pvo_patrimoine_voirie.pvoamenagementcyclable.4195","score":0.752204},
{"amenagement_id": "pvo_patrimoine_voirie.pvoamenagementcyclable.2158","score":0.763534},
{"amenagement_id": "pvo_patrimoine_voirie.pvoamenagementcyclable.130","score":0.75299},
{"amenagement_id": "pvo_patrimoine_voirie.pvoamenagementcyclable.2033","score":0.774191},
{"amenagement_id": "pvo_patrimoine_voirie.pvoamenagementcyclable.4177","score":0.795929},
{"amenagement_id": "pvo_patrimoine_voirie.pvoamenagementcyclable.4962","score":0.781875},
{"amenagement_id": "pvo_patrimoine_voirie.pvoamenagementcyclable.1909","score":0.725913},
{"amenagement_id": "pvo_patrimoine_voirie.pvoamenagementcyclable.4513"},
{"amenagement_id": "pvo_patrimoine_voirie.pvoamenagementcyclable.1509","score":0.781767},
{"amenagement_id": "pvo_patrimoine_voirie.pvoamenagementcyclable.2494","score":0.77943},
{"amenagement_id": "pvo_patrimoine_voirie.pvoamenagementcyclable.2487","score":0.800737},
{"amenagement_id": "pvo_patrimoine_voirie.pvoamenagementcyclable.7163","score":0.842378},
{"amenagement_id": "pvo_patrimoine_voirie.pvoamenagementcyclable.2104","score":0.812658},
{"amenagement_id": "pvo_patrimoine_voirie.pvoamenagementcyclable.2697","score":0.80862},
{"amenagement_id": "pvo_patrimoine_voirie.pvoamenagementcyclable.3539","score":0.85243},
{"amenagement_id": "pvo_patrimoine_voirie.pvoamenagementcyclable.3527","score":0.856603},
{"amenagement_id": "pvo_patrimoine_voirie.pvoamenagementcyclable.6503","score":0.863736},
{"amenagement_id": "pvo_patrimoine_voirie.pvoamenagementcyclable.2941","score":0.813314},
{"amenagement_id": "pvo_patrimoine_voirie.pvoamenagementcyclable.3709","score":0.880904},
{"amenagement_id": "pvo_patrimoine_voirie.pvoamenagementcyclable.4093","score":0.814909},
{"amenagement_id": "pvo_patrimoine_voirie.pvoamenagementcyclable.2845","score":0.8589},
{"amenagement_id": "pvo_patrimoine_voirie.pvoamenagementcyclable.5219"},
{"amenagement_id": "pvo_patrimoine_voirie.pvoamenagementcyclable.4112","score":0.875658},
{"amenagement_id": "pvo_patrimoine_voirie.pvoamenagementcyclable.4265","score":0.886232}]
